swh/core/__init__.py
swh/core/api_async.py
swh/core/collections.py
swh/core/config.py
swh/core/logger.py
swh/core/logging.py
swh/core/nar.py
swh/core/py.typed
swh/core/pytest_plugin.py
swh/core/retry.py
swh/core/sentry.py
swh/core/statsd.py
swh/core/tarball.py
swh/core/utils.py
swh/core/api/__init__.py
swh/core/api/asynchronous.py
swh/core/api/classes.py
swh/core/api/gunicorn_config.py
swh/core/api/negotiation.py
swh/core/api/serializers.py
swh/core/api/tests/__init__.py
swh/core/api/tests/server_testing.py
swh/core/api/tests/test_async.py
swh/core/api/tests/test_classes.py
swh/core/api/tests/test_gunicorn.py
swh/core/api/tests/test_init.py
swh/core/api/tests/test_rpc_client.py
swh/core/api/tests/test_rpc_client_server.py
swh/core/api/tests/test_rpc_server.py
swh/core/api/tests/test_rpc_server_asynchronous.py
swh/core/api/tests/test_serializers.py
swh/core/cli/__init__.py
swh/core/cli/backend.py
swh/core/cli/db.py
swh/core/cli/nar.py
swh/core/cli/sentry.py
swh/core/db/__init__.py
swh/core/db/common.py
swh/core/db/db_utils.py
swh/core/db/sql/35-dbversion.sql
swh/core/db/sql/36-dbmodule.sql
swh/core/db/tests/__init__.py
swh/core/db/tests/conftest.py
swh/core/db/tests/test_cli.py
swh/core/db/tests/test_db.py
swh/core/db/tests/test_db_utils.py
swh/core/db/tests/data/README
swh/core/db/tests/data/test/__init__.py
swh/core/db/tests/data/test/cli2/__init__.py
swh/core/db/tests/data/test/cli2/sql/0-superuser-init.sql
swh/core/db/tests/data/test/cli2/sql/30-schema.sql
swh/core/db/tests/data/test/cli2/sql/40-funcs.sql
swh/core/db/tests/data/test/cli2/sql/50-data.sql
swh/core/db/tests/data/test/cli2/sql/upgrades/001.sql
swh/core/db/tests/data/test/cli2/sql/upgrades/002.sql
swh/core/db/tests/data/test/cli2/sql/upgrades/003.sql
swh/core/db/tests/data/test/cli2/sql/upgrades/004.sql
swh/core/db/tests/data/test/cli2/sql/upgrades/005-bis.sql
swh/core/db/tests/data/test/cli2/sql/upgrades/005.sql
swh/core/db/tests/data/test/cli2/sql/upgrades/006.sql
swh_core-4.5.3.dist-info/licenses/AUTHORS
swh_core-4.5.3.dist-info/licenses/LICENSE
swh_core-4.5.3.dist-info/METADATA
swh_core-4.5.3.dist-info/WHEEL
swh_core-4.5.3.dist-info/entry_points.txt
swh_core-4.5.3.dist-info/top_level.txt
swh_core-4.5.3.dist-info/RECORD
